analise_dados/__init__.py
analise_dados/transformacoes.py
analise_dados/visualizacoes.py
analise_dados-0.1.0.dist-info/METADATA
analise_dados-0.1.0.dist-info/WHEEL
analise_dados-0.1.0.dist-info/RECORD
