Metadata-Version: 2.1
Name: analise-dados
Version: 0.1.0
Summary: Uma biblioteca simples para transformações e visualizações de dados
Author: Your Name
Author-email: you@example.com
Requires-Python: >=3.12,<4.0
Classifier: Programming Language :: Python :: 3
Classifier: Programming Language :: Python :: 3.12
Classifier: Programming Language :: Python :: 3.13
Requires-Dist: matplotlib (>=3.10.0,<4.0.0)
Requires-Dist: pandas (>=2.2.3,<3.0.0)
